Workbook

Sheet Sheet1
B1: Whatsapp | C1: Donatur | D1: CRM | E1: start_date | F1: No
A2: 0 | B2: 6281348526369 | C2: Mustakim | D2: WA_7778 | E2: 45931
A3: 1 | B3: 6285255859869 | C3: Nurhikmah | D3: WA_7778 | E3: 45931
A4: 2 | B4: 6285273861086 | C4: Khasndra | D4: WA_7778 | E4: 45931
A5: 3 | B5: 6285273908199 | C5: Dewi Sartika | D5: WA_7778 | E5: 45931
A6: 4 | B6: 6281330740765 | C6: Rusdi | D6: WA_7778 | E6: 45931
A7: 5 | B7: 6285274159404 | C7: Ernawati Nusi | D7: WA_7778 | E7: 45931
A8: 6 | B8: 6285276294437 | C8: Hamba Allah | D8: WA_7778 | E8: 45931
A9: 7 | B9: 6281328742768 | C9: hamba alloh | D9: WA_7778 | E9: 45931
A10: 8 | B10: 6285277660331 | C10: Asrihasan | D10: WA_7778 | E10: 45931
A11: 9 | B11: 6285277893569 | C11: Hermiana br sihombing | D11: WA_7778 | E11: 45931
A12: 10 | B12: 6285275375159 | C12: Nurul Hidayah | D12: WA_7778 | E12: 45931
A13: 11 | B13: 6285259091917 | C13: Lionel | D13: WA_7778 | E13: 45931
... A88: 86 | B88: 6281293261968 | C88: Hamba alloh | D88: WA_7778 | E88: 45931
A89: 87 | B89: 6285342706561 | C89: BundaHafizHadiq | D89: Eliminated
A90: 88 | B90: 6281310701768 | C90: iren rachman | D90: WA_7778 | E90: 45931
A91: 89 | B91: 6281310535582 | C91: Saodah Yoni | D91: WA_7778 | E91: 45931
A92: 90 | B92: 6285343684355 | C92: Kamaria Badaring | D92: WA_7778 | E92: 45931
A93: 91 | B93: 6281365618979 | C93: Firdaus bin samiakfirda salon | D93: WA_7778 | E93: 45931
A94: 92 | B94: 6285343757834 | C94: Sartika Wati | D94: WA_7778 | E94: 45931
A95: 93 | B95: 6285344113747 | C95: Theresia oktavini | D95: WA_7778 | E95: 45931
A96: 94 | B96: 6281310249945 | C96: Siti Khairiyah | D96: WA_7778 | E96: 45931
A97: 95 | B97: 6285240387411 | C97: Moh Taufiq kumali | D97: WA_7778 | E97: 45931
A98: 96 | B98: 6285239620497 | C98: Sumarni | D98: WA_7778 | E98: 45931
A99: 97 | B99: 6285347459963 | C99: Diana | D99: WA_7778 | E99: 45931
A100: 98 | B100: 6285349452081 | C100: Anton | D100: WA_7778 | E100: 45931
A101: 99 | B101: 6281366146555 | C101: Nopriyandi | D101: WA_7778 | E101: 45931
... A182: 180 | B182: 6282183836604 | C182: Januar iskandar muda | D182: WA_7778 | E182: 45931
A183: 181 | B183: 628126478757 | C183: Noviandri | D183: Eliminated
A184: 182 | B184: 6287875265156 | C184: Nida Nurma Utami | D184: WA_7778 | E184: 45931
A185: 183 | B185: 6282143997273 | C185: Prapti M | D185: WA_7778 | E185: 45931
A186: 184 | B186: 6282285668796 | C186: Nandang sahyana | D186: WA_7778 | E186: 45931
A187: 185 | B187: 628126728557 | C187: Ratnawilis | D187: WA_7778 | E187: 45931
A188: 186 | B188: 6282143394948 | C188: fatma rindu | D188: WA_7778 | E188: 45931
A189: 187 | B189: 6282252317779 | C189: Ida Royanti | D189: WA_7778 | E189: 45931
A190: 188 | B190: 6282250220204 | C190: Syamsuddin | D190: WA_7778 | E190: 45931
A191: 189 | B191: 628125100716 | C191: Pribakti Budinurdjaja | D191: WA_7778 | E191: 45931
A192: 190 | B192: 6282137364579 | C192: Dapur Pakde Falah | D192: WA_7778 | E192: 45931
A193: 191 | B193: 6287838846543 | C193: Munir | D193: WA_7778 | E193: 45931
A194: 192 | B194: 62818591940 | C194: Ike | D194: WA_7778 | E194: 45931
A195: 193 | B195: 6282245415413 | C195: rhm | D195: WA_7778 | E195: 45931
... A210: 208 | B210: 6287783216030 | C210: Dodi Hidayat | D210: WA_7778 | E210: 45931
A211: 209 | B211: 6282196951900 | C211: Hamba Allah | D211: Eliminated
A212: 210 | B212: 6282126318807 | C212: Eli Laeliyah | D212: WA_7778 | E212: 45931
A213: 211 | B213: 6287782162979 | C213: Yolanda | D213: WA_7778 | E213: 45931
A214: 212 | B214: 6287781188033 | C214: Sunarjo | D214: WA_7778 | E214: 45931
A215: 213 | B215: 6282310138101 | C215: Mayani Rais | D215: WA_7778 | E215: 45931
A216: 214 | B216: 6282298890755 | C216: Marni | D216: WA_7778 | E216: 45931
A217: 215 | B217: 6282130752006 | C217: Asmui | D217: WA_7778 | E217: 45931
A218: 216 | B218: 6282298555882 | C218: Nunuk Kurniawati | D218: WA_7778 | E218: 45931
A219: 217 | B219: 62852443010099 | C219: Tiky Agil Uar | D219: WA_7778 | E219: 45931
A220: 218 | B220: 6282135916608 | C220: mr Idris | D220: WA_7778 | E220: 45931
A221: 219 | B221: 6287837954321 | C221: Danang | D221: WA_7778 | E221: 45931
A222: 220 | B222: 6282190171557 | C222: Rury | D222: WA_7778 | E222: 45931
A223: 221 | B223: 6282190577744 | C223: Afrizal Azhar Aidis | D223: WA_7778 | E223: 45931
... A306: 304 | B306: 6282148776196 | C306: Hamba Allah | D306: WA_7778 | E306: 45931
A307: 305 | B307: 6282181117566 | C307: Hamba allah | D307: Eliminated
A308: 306 | B308: 6282153190677 | C308: Ainun Parida | D308: WA_7778 | E308: 45931
A309: 307 | B309: 6282242967717 | C309: Dino Dino | D309: WA_7778 | E309: 45931
A310: 308 | B310: 6282153980001 | C310: Muzahar | D310: WA_7778 | E310: 45931
A311: 309 | B311: 6288216001226 | C311: Rahmad Wahyu Hidayat | D311: WA_7778 | E311: 45931
A312: 310 | B312: 6288215456509 | C312: Ahsan | D312: WA_7778 | E312: 45931
A313: 311 | B313: 6288213435160 | C313: Arya | D313: WA_7778 | E313: 45931
A314: 312 | B314: 6282280343193 | C314: Nasrullah | D314: WA_7778 | E314: 45931
A315: 313 | B315: 6282280378611 | C315: Hamba Allah | D315: Eliminated
A316: 314 | B316: 6282156618997 | C316: Siti Aisyah | D316: WA_7778 | E316: 45931
A317: 315 | B317: 6282155565475 | C317: Susi susanti | D317: WA_7778 | E317: 45931
A318: 316 | B318: 6282255105125 | C318: Hasnawati | D318: Eliminated
A319: 317 | B319: 6282281242677 | C319: Hamba Allah | D319: WA_7778 | E319: 45931
A320: 318 | B320: 6282177477412 | C320: Yuni | D320: WA_7778 | E320: 45931
A321: 319 | B321: 6287889001409 | C321: Meiky Pandu | D321: WA_7778 | E321: 45931
A322: 320 | B322: 6289661241015 | C322: Zulva | D322: WA_7778 | E322: 45931
A323: 321 | B323: 6282154736766 | C323: Andi Rini I | D323: WA_7778 | E323: 45931
A324: 322 | B324: 6282154611615 | C324: Wahdan nur | D324: WA_7778 | E324: 45931
A325: 323 | B325: 628113702233 | C325: Imam Syah | D325: WA_7778 | E325: 45931
A326: 324 | B326: 6282254834469 | C326: Amrani | D326: WA_7778 | E326: 45931
A327: 325 | B327: 6282154196614 | C327: Siti Asriyah | D327: WA_7778 | E327: 45931
A328: 326 | B328: 6282178543380 | C328: Hendro Aprizal | D328: WA_7778 | E328: 45931
A329: 327 | B329: 6282178550438 | C329: Supriadi | D329: WA_7778 | E329: 45931
A330: 328 | B330: 628123353170 | C330: Ony Yunantha | D330: WA_7778 | E330: 45931
... A508: 506 | B508: 6282227472646 | C508: Rizky Ali fahrudin | D508: WA_7778 | E508: 45931
A509: 507 | B509: 6285234882549 | C509: Edy Susilo | D509: Eliminated
A510: 508 | B510: 6285234591551 | C510: Amir | D510: WA_7778 | E510: 45931
A511: 509 | B511: 6282227389999 | C511: Sulaiman | D511: WA_7778 | E511: 45931
A512: 510 | B512: 6285234449999 | C512: Farisy | D512: WA_7778 | E512: 45931
A513: 511 | B513: 6285233122639 | C513: Hamba Allah | D513: WA_7778 | E513: 45931
A514: 512 | B514: 6285261175119 | C514: Sunartin | D514: WA_7778 | E514: 45931
A515: 513 | B515: 6282256447917 | C515: Saidil | D515: WA_7778 | E515: 45931
A516: 514 | B516: 6282256549695 | C516: Dwi Rahayu Ningsih | D516: WA_7778 | E516: 45931
A517: 515 | B517: 6282227350770 | C517: hana | D517: WA_7778 | E517: 45931
A518: 516 | B518: 6282256615773 | C518: Hariyati | D518: WA_7778 | E518: 45931
A519: 517 | B519: 6285232933111 | C519: Tarson Effendi | D519: WA_7778 | E519: 45931
A520: 518 | B520: 6285231390114 | C520: Anjelia Laurensia | D520: WA_7778 | E520: 45931
A521: 519 | B521: 6285231361557 | C521: Abdul Muthalib rahimahullah | D521: WA_7778 | E521: 45931
... A582: 580 | B582: 6282244580580 | C582: iman santoso | D582: WA_7778 | E582: 45931
A583: 581 | B583: 6282245098470 | C583: Tantri Panggih | D583: Eliminated
A584: 582 | B584: 6285252961631 | C584: Hamba Allah | D584: WA_7778 | E584: 45931
A585: 583 | B585: 6285253929879 | C585: Hamba Allah | D585: WA_7778 | E585: 45931
A586: 584 | B586: 6282245112217 | C586: Benny | D586: WA_7778 | E586: 45931
A587: 585 | B587: 6285249403909 | C587: Ahmad | D587: WA_7778 | E587: 45931
...

Sheet Sheet2
A1: nomor | B1: wa
A2: 6281280258518 | B2: =VLOOKUP(A2,Sheet1!$B$2:$D$70347,3,0) -> WA_2057_1 | E2: Row Labels | F2: Count of nomor
A3: 6287786602539 | B3: =VLOOKUP(A3,Sheet1!$B$2:$D$70347,3,0) -> WA_2057_1 | E3: Refill_WA_2058_2 | F3: 23
A4: 6285240407337 | B4: =VLOOKUP(A4,Sheet1!$B$2:$D$70347,3,0) -> WA_2057_1 | E4: WA_2056_1 | F4: 1
A5: 628113312332 | B5: =VLOOKUP(A5,Sheet1!$B$2:$D$70347,3,0) -> WA_2057_1 | E5: WA_2057_1 | F5: 484
A6: 6281365319444 | B6: =VLOOKUP(A6,Sheet1!$B$2:$D$70347,3,0) -> WA_2057_1 | E6: WA_2060_2 | F6: 487
A7: 6281244075707 | B7: =VLOOKUP(A7,Sheet1!$B$2:$D$70347,3,0) -> WA_2057_1 | E7: #N/A | F7: 7
A8: 6287878139524 | B8: =VLOOKUP(A8,Sheet1!$B$2:$D$70347,3,0) -> WA_2057_1 | E8: (blank)
A9: 6288213142414 | B9: =VLOOKUP(A9,Sheet1!$B$2:$D$70347,3,0) -> WA_2057_1 | E9: Grand Total | F9: 1002
A10: 6285233531300 | B10: =VLOOKUP(A10,Sheet1!$B$2:$D$70347,3,0) -> WA_2057_1
A11: 6281266705556 | B11: =VLOOKUP(A11,Sheet1!$B$2:$D$70347,3,0) -> WA_2057_1
A12: 6285277685171 | B12: =VLOOKUP(A12,Sheet1!$B$2:$D$70347,3,0) -> WA_2057_1
A13: 6285364753541 | B13: =VLOOKUP(A13,Sheet1!$B$2:$D$70347,3,0) -> WA_2057_1
A14: 628126628810 | B14: =VLOOKUP(A14,Sheet1!$B$2:$D$70347,3,0) -> WA_2057_1
A15: 6281296288677 | B15: =VLOOKUP(A15,Sheet1!$B$2:$D$70347,3,0) -> WA_2057_1
A16: 628111667204 | B16: =VLOOKUP(A16,Sheet1!$B$2:$D$70347,3,0) -> WA_2057_1
A17: 6287877830094 | B17: =VLOOKUP(A17,Sheet1!$B$2:$D$70347,3,0) -> WA_2057_1
A18: 6282224269730 | B18: =VLOOKUP(A18,Sheet1!$B$2:$D$70347,3,0) -> WA_2057_1
A19: 6289662971198 | B19: =VLOOKUP(A19,Sheet1!$B$2:$D$70347,3,0) -> WA_2057_1
A20: 6281380539989 | B20: =VLOOKUP(A20,Sheet1!$B$2:$D$70347,3,0) -> WA_2057_1
A21: 6281372826128 | B21: =VLOOKUP(A21,Sheet1!$B$2:$D$70347,3,0) -> WA_2057_1
... A1003: 6282110734086 | B1003: =VLOOKUP(A1003,Sheet1!$B$2:$D$70347,3,0) -> WA_2057_1
